Metadata-Version: 2.1
Name: serverless-event-mocks
Version: 0.0.6
Summary: A small Python library that includes details mocks of AWS Lambda event sources.
Home-page: https://github.com/abirhoss/serverless-event-mocks
Author: Abir Hossain
Author-email: abirz.pro@gmail.com
License: MIT
Download-URL: https://github.com/abirhoss/serverless-event-mocks/archive/v0.0.6.tar.gz
Keywords: serverless,serverless-framework,unittest,mock,events,aws-lambda
Platform: UNKNOWN
Classifier: Development Status :: 4 - Beta
Classifier: Programming Language :: Python :: 3
Classifier: License :: OSI Approved :: MIT License
Classifier: Operating System :: OS Independent
